README.rst
setup.py
cardboardlint/__init__.py
cardboardlint/__main__.py
cardboardlint/cli.py
cardboardlint/diff.py
cardboardlint/linter.py
cardboardlint/linter_autopep8.py
cardboardlint/linter_black.py
cardboardlint/linter_cppcheck.py
cardboardlint/linter_cpplint.py
cardboardlint/linter_doxygen.py
cardboardlint/linter_flake8.py
cardboardlint/linter_header.py
cardboardlint/linter_import.py
cardboardlint/linter_namespace.py
cardboardlint/linter_pycodestyle.py
cardboardlint/linter_pydocstyle.py
cardboardlint/linter_pylint.py
cardboardlint/linter_rst_lint.py
cardboardlint/linter_whitespace.py
cardboardlint/linter_yamllint.py
cardboardlint/linter_yapf.py
cardboardlint/report.py
cardboardlint/utils.py
cardboardlint/version.py
cardboardlint.egg-info/PKG-INFO
cardboardlint.egg-info/SOURCES.txt
cardboardlint.egg-info/dependency_links.txt
cardboardlint.egg-info/entry_points.txt
cardboardlint.egg-info/requires.txt
cardboardlint.egg-info/top_level.txt
cardboardlint/test/__init__.py
cardboardlint/test/test_cli.py
cardboardlint/test/test_diff.py
cardboardlint/test/test_linter.py
cardboardlint/test/test_report.py
cardboardlint/test/test_utils.py